hydra_config/__init__.py
hydra_config/_version.py
hydra_config/cli.py
hydra_config/config.py
hydra_config/resolvers.py
hydra_config/utils.py
hydra_config-0.0.15.dist-info/licenses/LICENSE
hydra_config-0.0.15.dist-info/METADATA
hydra_config-0.0.15.dist-info/WHEEL
hydra_config-0.0.15.dist-info/top_level.txt
hydra_config-0.0.15.dist-info/RECORD
