Metadata-Version: 2.4
Name: hydra-config
Version: 0.0.15
Summary: Enhanced Hydra structured configs
Requires-Python: >=3.11
License-File: LICENSE
Requires-Dist: pyyaml>=6.0.2
Requires-Dist: RestrictedPython>=7.4
Requires-Dist: hydra_zen>=0.13.0
Requires-Dist: omegaconf>=2.3.0
Requires-Dist: hydra-core>=1.3.2
Provides-Extra: dev
Requires-Dist: black>=24.8.0; extra == "dev"
Requires-Dist: flake8>=7.1.1; extra == "dev"
Requires-Dist: Flake8-pyproject>=1.2.3; extra == "dev"
Requires-Dist: isort>=5.13.2; extra == "dev"
Requires-Dist: pyright>=1.1.381; extra == "dev"
Requires-Dist: pytest>=8.3.3; extra == "dev"
Requires-Dist: pre-commit>=3.8.0; extra == "dev"
Provides-Extra: docs
Requires-Dist: sphinx>=7.2.6; extra == "docs"
Requires-Dist: furo>=2024.8.6; extra == "docs"
Requires-Dist: sphinx-autoapi>=3.4.0; extra == "docs"
Requires-Dist: sphinx-autobuild>=2024.10.3; extra == "docs"
Requires-Dist: sphinx-copybutton>=0.5.2; extra == "docs"
Requires-Dist: myst-parser>=4.0.0; extra == "docs"
Requires-Dist: sphinxcontrib-video>=0.3.1; extra == "docs"
Requires-Dist: sphinxcontrib-googleanalytics>=0.4; extra == "docs"
Dynamic: license-file
